grapheme/__init__.py
grapheme/api.py
grapheme/finder.py
grapheme/grapheme_property_group.py
grapheme/data/grapheme_break_property.json
grapheme-0.5.0.dist-info/LICENSE
grapheme-0.5.0.dist-info/METADATA
grapheme-0.5.0.dist-info/WHEEL
grapheme-0.5.0.dist-info/top_level.txt
grapheme-0.5.0.dist-info/RECORD
