Metadata-Version: 2.1
Name: grapheme
Version: 0.5.0
Summary: Unicode grapheme helpers
Home-page: https://github.com/alvinlindstam/grapheme
Author: Alvin Lindstam
Author-email: alvin.lindstam@gmail.com
License: MIT
Platform: UNKNOWN
Classifier: Development Status :: 3 - Alpha
Classifier: Intended Audience :: Developers
Classifier: Programming Language :: Python
Classifier: Programming Language :: Python :: 3
Classifier: Programming Language :: Python :: 3.3
Classifier: Programming Language :: Python :: 3.4
Classifier: Programming Language :: Python :: 3.5
Classifier: Programming Language :: Python :: 3.6
Provides-Extra: test
